dxrt/__init__.py
dxrt/pokemon.csv
dxrt/random_pokemon.py
dxrt-1.0.4.dist-info/METADATA
dxrt-1.0.4.dist-info/WHEEL
dxrt-1.0.4.dist-info/top_level.txt
dxrt-1.0.4.dist-info/RECORD
