Metadata-Version: 2.1
Name: dxrt
Version: 1.0.4
Summary: Libreria para generar un pokemon aleatorio
Author: Gael Peña
Author-email: gaelpeje1@gmail.com
Requires-Dist: pandas
